LICENSE
MANIFEST.in
README.md
setup.py
src/django_drynk.egg-info/.DS_Store
src/django_drynk.egg-info/PKG-INFO
src/django_drynk.egg-info/SOURCES.txt
src/django_drynk.egg-info/dependency_links.txt
src/django_drynk.egg-info/requires.txt
src/django_drynk.egg-info/top_level.txt
src/drynk/__init__.py
src/drynk/decorators.py